depigraph.py
depigraph-0.6.0.dist-info/DESCRIPTION.rst
depigraph-0.6.0.dist-info/METADATA
depigraph-0.6.0.dist-info/RECORD
depigraph-0.6.0.dist-info/WHEEL
depigraph-0.6.0.dist-info/entry_points.txt
depigraph-0.6.0.dist-info/metadata.json
depigraph-0.6.0.dist-info/top_level.txt
