Metadata-Version: 2.0
Name: depigraph
Version: 0.6.0
Summary: Draw dependency graphs for python distributions
Home-page: https://github.com/warner/depigraph
Author: Brian Warner
Author-email: warner-depigraph@lothar.com
License: MIT
Platform: UNKNOWN
Requires-Dist: click
